{"22c54789-4693-4152-a364-f10c6f6ec671":{"DK2PKV":{"shortUrl":"DK2PKV","longUrl":"https://classroom.google.com/u/0/c/NTQ0NTgzNTA1ODMx"},"vpS1Go":{"shortUrl":"vpS1Go","longUrl":"https://github.com/adlascio-instructor/mid-term-tinylinks-juan-david"},"ld0BHR":{"shortUrl":"ld0BHR","longUrl":"asdf"},"4UPxKb":{"shortUrl":"4UPxKb","longUrl":"test.com"},"W4PQHA":{"shortUrl":"W4PQHA","longUrl":"leetcode.com"}},"a1d922a2-06f2-47df-8626-3b4b0b8ccf0a":{"N7qDOW":{"shortUrl":"N7qDOW","longUrl":"a"},"lOGnSW":{"shortUrl":"lOGnSW","longUrl":"https://leetcode.com/"}},"720bd2c9-3034-4ef5-9271-fe6917fd787e":{"76rnhq":{"shortUrl":"76rnhq","longUrl":"www.leetcode.com"},"B12194":{"shortUrl":"B12194","longUrl":"leetcode.com"}}}